rstoys/__init__.py
rstoys/geo/__init__.py
rstoys/maps/__init__.py
rstoys/realtime/__init__.py
rstoys/touchy/__init__.py
rstoys/touchy/static/stick-back.png
rstoys/touchy/static/stick1-back.jpg
rstoys/touchy/static/stick1-top.png
rstoys/touchy/templates/touchy.html
rstoys-1.1.3.dist-info/LICENSE
rstoys-1.1.3.dist-info/METADATA
rstoys-1.1.3.dist-info/WHEEL
rstoys-1.1.3.dist-info/top_level.txt
rstoys-1.1.3.dist-info/RECORD
