Metadata-Version: 2.1
Name: rstoys
Version: 1.1.3
Summary: Library for simple real-time control of robotic toys.
Home-page: https://github.com/rstgh/rstoys
Author: Radek Szamrej
Author-email: rstechnology@gmail.com
License: MIT
Platform: UNKNOWN
